TallerProgramacion/Aplicacion.py
TallerProgramacion/__init__.py
Taller_Programacion_Walter25-1.0.0.dist-info/LICENSE.txt
Taller_Programacion_Walter25-1.0.0.dist-info/METADATA
Taller_Programacion_Walter25-1.0.0.dist-info/WHEEL
Taller_Programacion_Walter25-1.0.0.dist-info/top_level.txt
Taller_Programacion_Walter25-1.0.0.dist-info/RECORD
